{
  "timestamp": "2026-04-25T10:57:36.360693+00:00",
  "architecture": "vsm-lm-v6-mlx",
  "step": 500,
  "config": {
    "d_model": 512,
    "d_register": 128,
    "d_ff": 1536,
    "d_ff_consolidate": 2048,
    "n_heads": 8,
    "strides": [
      1,
      8,
      16,
      32,
      64,
      128,
      256,
      512,
      1024
    ],
    "window": 8,
    "vocab_size": 50277,
    "seq_len": 4096,
    "alpha": 1.18,
    "n_passes": 5,
    "pass_names": [
      "L0_asc",
      "L1_asc",
      "L2_apex",
      "L1_desc",
      "L0_desc"
    ],
    "phase_names": [
      "prep",
      "converge",
      "consolidate"
    ],
    "reg_names": [
      "type",
      "scope",
      "role"
    ],
    "total_ternary_weights": 35258368
  },
  "total_flips": 0,
  "flip_consensus": 50,
  "grad_norm": 0.5469432473182678,
  "train_loss": 6.519968152046204,
  "eval_loss": 6.827784585952759,
  "relational_loss": 0.5287146091007342,
  "excess_ppl": 125.2069730053751,
  "ppl": 678.5567743505138,
  "phi_compression": {
    "overall": {
      "L0_asc": {
        "mean_ratio": -0.461989539461221,
        "std_ratio": 0.3704247672147992,
        "mean_h_in": -0.18461635895073414,
        "mean_h_out": 0.0808478167746216,
        "phi_dev": 1.080023528211116,
        "direction": "compressing"
      },
      "L1_asc": {
        "mean_ratio": 3.604073339674138,
        "std_ratio": 9.92596146552727,
        "mean_h_in": 0.0808478167746216,
        "mean_h_out": 0.5633025150746107,
        "phi_dev": 2.986039350924243,
        "direction": "expanding"
      },
      "L2_apex": {
        "mean_ratio": 1.8115884017080013,
        "std_ratio": 0.14948101838284067,
        "mean_h_in": 0.5633025150746107,
        "mean_h_out": 1.002485129982233,
        "phi_dev": 1.1935544129581066,
        "direction": "expanding"
      },
      "L1_desc": {
        "mean_ratio": 1.335771688589074,
        "std_ratio": 0.048985052969572736,
        "mean_h_in": 1.002485129982233,
        "mean_h_out": 1.3300955221056938,
        "phi_dev": 0.7177376998391792,
        "direction": "expanding"
      },
      "L0_desc": {
        "mean_ratio": 1.2393803263985255,
        "std_ratio": 0.024802302446835428,
        "mean_h_in": 1.3300955221056938,
        "mean_h_out": 1.6432863548398018,
        "phi_dev": 0.6213463376486307,
        "direction": "expanding"
      },
      "aggregate": {
        "mean_ratio": 1.5057648433817037,
        "mean_phi_dev": 1.3197402659162552,
        "target": 0.6180339887498948
      },
      "loss": {
        "mean_loss": 7.644778937101364,
        "relational_loss": 0.6518425212963423,
        "excess_ppl": 385.59166124529975
      },
      "gates": {
        "L0_asc_prep": 0.5054441634565592,
        "L0_asc_converge": 0.892188124358654,
        "L0_asc_consolidate": 0.4794219508767128,
        "L1_asc_prep": 0.5245859250426292,
        "L1_asc_converge": 0.9333447441458702,
        "L1_asc_consolidate": 0.5699946545064449,
        "L2_apex_prep": 0.5694423355162144,
        "L2_apex_converge": 0.9165111593902111,
        "L2_apex_consolidate": 0.6335727125406265,
        "L1_desc_prep": 0.6537290215492249,
        "L1_desc_converge": 0.9109307937324047,
        "L1_desc_consolidate": 0.6953987963497639,
        "L0_desc_prep": 0.6919737979769707,
        "L0_desc_converge": 0.8969472981989384,
        "L0_desc_consolidate": 0.7185396254062653
      },
      "mod_mean": {
        "L0_asc_prep": -0.0002391614361840766,
        "L0_asc_converge": -0.001295351336011663,
        "L0_asc_consolidate": -0.004849454926443286,
        "L1_asc_prep": -0.002063443153588196,
        "L1_asc_converge": -0.0009034893446369097,
        "L1_asc_consolidate": -0.006681689876131713,
        "L2_apex_prep": -0.003641617666289676,
        "L2_apex_converge": -0.0017084009523387067,
        "L2_apex_consolidate": -0.00761473439342808,
        "L1_desc_prep": -0.004575896622554865,
        "L1_desc_converge": -0.003764541209420713,
        "L1_desc_consolidate": -0.008441172583843581,
        "L0_desc_prep": -0.004833607803448103,
        "L0_desc_converge": -0.00266340932193998,
        "L0_desc_consolidate": -0.00805974229297135
      },
      "mod_std": {
        "L0_asc_prep": 0.1385608846321702,
        "L0_asc_converge": 0.5348480101674795,
        "L0_asc_consolidate": 0.15617023408412933,
        "L1_asc_prep": 0.14553094562143087,
        "L1_asc_converge": 0.5705803390592337,
        "L1_asc_consolidate": 0.18992723431438208,
        "L2_apex_prep": 0.15996164362877607,
        "L2_apex_converge": 0.5536501854658127,
        "L2_apex_consolidate": 0.21180630009621382,
        "L1_desc_prep": 0.18450055737048388,
        "L1_desc_converge": 0.5345140099525452,
        "L1_desc_consolidate": 0.23159638326615095,
        "L0_desc_prep": 0.19646160304546356,
        "L0_desc_converge": 0.5256735291332006,
        "L0_desc_consolidate": 0.2379747461527586
      },
      "meta_gates": {
        "L0_asc": 0.9999382011592388,
        "L1_asc": 0.9999569542706013,
        "L2_apex": 0.9999097511172295,
        "L1_desc": 0.9999209642410278,
        "L0_desc": 0.9999490082263947
      },
      "write_gates": {
        "L0_asc_prep_write_type": 0.6920913197100163,
        "L0_asc_prep_write_scope": 0.8339005596935749,
        "L0_asc_prep_write_role": 0.8623537868261337,
        "L0_asc_converge_write_type": 0.09387278708163649,
        "L0_asc_converge_write_scope": 0.37850550236180425,
        "L0_asc_converge_write_role": 0.7196095084909757,
        "L0_asc_consolidate_write_type": 0.45189953222870827,
        "L0_asc_consolidate_write_scope": 0.1790433507412672,
        "L0_asc_consolidate_write_role": 0.2512653823941946,
        "L1_asc_prep_write_type": 0.7676386535167694,
        "L1_asc_prep_write_scope": 0.9278758950531483,
        "L1_asc_prep_write_role": 0.8397068679332733,
        "L1_asc_converge_write_type": 0.2978705237037502,
        "L1_asc_converge_write_scope": 0.03469195944489911,
        "L1_asc_converge_write_role": 0.7589341998100281,
        "L1_asc_consolidate_write_type": 0.29072831152006984,
        "L1_asc_consolidate_write_scope": 0.2878633886575699,
        "L1_asc_consolidate_write_role": 0.33655698224902153,
        "L2_apex_prep_write_type": 0.7802883684635162,
        "L2_apex_prep_write_scope": 0.8814939223229885,
        "L2_apex_prep_write_role": 0.19194979313760996,
        "L2_apex_converge_write_type": 0.5093212961219251,
        "L2_apex_converge_write_scope": 0.7317212946556992,
        "L2_apex_converge_write_role": 0.38177569834147107,
        "L2_apex_consolidate_write_type": 0.12188937328755856,
        "L2_apex_consolidate_write_scope": 0.15476957708597183,
        "L2_apex_consolidate_write_role": 0.1309900670312345,
        "L1_desc_prep_write_type": 0.5700337197631598,
        "L1_desc_prep_write_scope": 0.626387219876051,
        "L1_desc_prep_write_role": 0.9122373834252357,
        "L1_desc_converge_write_type": 0.008182850078924275,
        "L1_desc_converge_write_scope": 0.7547027207911015,
        "L1_desc_converge_write_role": 0.488587211817503,
        "L1_desc_consolidate_write_type": 0.22026881761848927,
        "L1_desc_consolidate_write_scope": 0.17898353189229965,
        "L1_desc_consolidate_write_role": 0.12201929651200771,
        "L0_desc_prep_write_type": 0.1406354154460132,
        "L0_desc_prep_write_scope": 0.6217228583991528,
        "L0_desc_prep_write_role": 0.04826621408574283,
        "L0_desc_converge_write_type": 0.9128422737121582,
        "L0_desc_converge_write_scope": 0.8276353627443314,
        "L0_desc_converge_write_role": 0.14615487647552072,
        "L0_desc_consolidate_write_type": 0.12263404950499535,
        "L0_desc_consolidate_write_scope": 0.38148538395762444,
        "L0_desc_consolidate_write_role": 0.04022153664845973
      },
      "strides": {
        "L0_asc_stride_0_s1_ratio": -0.8049126962536058,
        "L0_asc_stride_0_s1_delta_norm": 14.587698936462402,
        "L0_asc_stride_0_s1_rel_contrib": 0.6616249134662826,
        "L0_asc_stride_1_s8_ratio": 4.9250360278934195,
        "L0_asc_stride_1_s8_delta_norm": 21.157692432403564,
        "L0_asc_stride_1_s8_rel_contrib": 0.7964135698213218,
        "L0_asc_stride_2_s16_ratio": 1.6801093888413925,
        "L0_asc_stride_2_s16_delta_norm": 24.801336884498596,
        "L0_asc_stride_2_s16_rel_contrib": 0.7249591389741795,
        "L0_asc_stride_3_s32_ratio": 1.3352041765936509,
        "L0_asc_stride_3_s32_delta_norm": 26.42192041873932,
        "L0_asc_stride_3_s32_rel_contrib": 0.6222336834148893,
        "L0_asc_stride_4_s64_ratio": 1.2090486640760596,
        "L0_asc_stride_4_s64_delta_norm": 27.501657962799072,
        "L0_asc_stride_4_s64_rel_contrib": 0.5404400902413071,
        "L0_asc_stride_5_s128_ratio": 1.1449073167433492,
        "L0_asc_stride_5_s128_delta_norm": 27.908732414245605,
        "L0_asc_stride_5_s128_rel_contrib": 0.4730557488533731,
        "L0_asc_stride_6_s256_ratio": 1.098211931657751,
        "L0_asc_stride_6_s256_delta_norm": 26.772644877433777,
        "L0_asc_stride_6_s256_rel_contrib": 0.4005531108228039,
        "L0_asc_stride_7_s512_ratio": 1.0838022526967044,
        "L0_asc_stride_7_s512_delta_norm": 26.690401911735535,
        "L0_asc_stride_7_s512_rel_contrib": 0.3622003734472648,
        "L0_asc_stride_8_s1024_ratio": 1.0675188814715493,
        "L0_asc_stride_8_s1024_delta_norm": 27.796512007713318,
        "L0_asc_stride_8_s1024_rel_contrib": 0.34477366695634953,
        "L0_asc_stride_mean_ratio": 1.4154362159689189,
        "L1_asc_stride_0_s1_ratio": 6.222747206777276,
        "L1_asc_stride_0_s1_delta_norm": 16.75553071498871,
        "L1_asc_stride_0_s1_rel_contrib": 0.6223115736317867,
        "L1_asc_stride_1_s8_ratio": 2.1807367150084795,
        "L1_asc_stride_1_s8_delta_norm": 21.67291760444641,
        "L1_asc_stride_1_s8_rel_contrib": 0.6797870054706925,
        "L1_asc_stride_2_s16_ratio": 1.4863843080563313,
        "L1_asc_stride_2_s16_delta_norm": 24.752943754196167,
        "L1_asc_stride_2_s16_rel_contrib": 0.6359353497212533,
        "L1_asc_stride_3_s32_ratio": 1.2911423469364658,
        "L1_asc_stride_3_s32_delta_norm": 26.314042687416077,
        "L1_asc_stride_3_s32_rel_contrib": 0.5657727091266358,
        "L1_asc_stride_4_s64_ratio": 1.1949259667126335,
        "L1_asc_stride_4_s64_delta_norm": 27.61027765274048,
        "L1_asc_stride_4_s64_rel_contrib": 0.5054265498474966,
        "L1_asc_stride_5_s128_ratio": 1.1365463829524955,
        "L1_asc_stride_5_s128_delta_norm": 27.98455536365509,
        "L1_asc_stride_5_s128_rel_contrib": 0.44841907572856426,
        "L1_asc_stride_6_s256_ratio": 1.0951665593539126,
        "L1_asc_stride_6_s256_delta_norm": 27.159537196159363,
        "L1_asc_stride_6_s256_rel_contrib": 0.387223367095409,
        "L1_asc_stride_7_s512_ratio": 1.0833118728601656,
        "L1_asc_stride_7_s512_delta_norm": 26.5641667842865,
        "L1_asc_stride_7_s512_rel_contrib": 0.34436476376681335,
        "L1_asc_stride_8_s1024_ratio": 1.0663892504068704,
        "L1_asc_stride_8_s1024_delta_norm": 27.59289848804474,
        "L1_asc_stride_8_s1024_rel_contrib": 0.32792082830311775,
        "L1_asc_stride_mean_ratio": 1.8619278454516255,
        "L2_apex_stride_0_s1_ratio": 1.2492788026357695,
        "L2_apex_stride_0_s1_delta_norm": 18.287256360054016,
        "L2_apex_stride_0_s1_rel_contrib": 0.5022045811519963,
        "L2_apex_stride_1_s8_ratio": 1.3685021316151489,
        "L2_apex_stride_1_s8_delta_norm": 21.788620471954346,
        "L2_apex_stride_1_s8_rel_contrib": 0.5310255459389623,
        "L2_apex_stride_2_s16_ratio": 1.2596762111599582,
        "L2_apex_stride_2_s16_delta_norm": 24.298811674118042,
        "L2_apex_stride_2_s16_rel_contrib": 0.5179316280614729,
        "L2_apex_stride_3_s32_ratio": 1.1976351731440364,
        "L2_apex_stride_3_s32_delta_norm": 25.761825442314148,
        "L2_apex_stride_3_s32_rel_contrib": 0.48370181876954715,
        "L2_apex_stride_4_s64_ratio": 1.1578395520809242,
        "L2_apex_stride_4_s64_delta_norm": 27.383700847625732,
        "L2_apex_stride_4_s64_rel_contrib": 0.4558309582058537,
        "L2_apex_stride_5_s128_ratio": 1.1092599501769977,
        "L2_apex_stride_5_s128_delta_norm": 27.152872562408447,
        "L2_apex_stride_5_s128_rel_contrib": 0.40590440292004604,
        "L2_apex_stride_6_s256_ratio": 1.0841230212476953,
        "L2_apex_stride_6_s256_delta_norm": 27.002313375473022,
        "L2_apex_stride_6_s256_rel_contrib": 0.36693772739537545,
        "L2_apex_stride_7_s512_ratio": 1.0703959164394858,
        "L2_apex_stride_7_s512_delta_norm": 25.85692846775055,
        "L2_apex_stride_7_s512_rel_contrib": 0.3231186008332011,
        "L2_apex_stride_8_s1024_ratio": 1.0621951430086234,
        "L2_apex_stride_8_s1024_delta_norm": 27.23180341720581,
        "L2_apex_stride_8_s1024_rel_contrib": 0.3162953585627282,
        "L2_apex_stride_mean_ratio": 1.1732117668342934,
        "L1_desc_stride_0_s1024_ratio": 1.3098734119224165,
        "L1_desc_stride_0_s1024_delta_norm": 26.40468454360962,
        "L1_desc_stride_0_s1024_rel_contrib": 0.5542907914619366,
        "L1_desc_stride_1_s512_ratio": 1.1736351476330464,
        "L1_desc_stride_1_s512_delta_norm": 26.082610726356506,
        "L1_desc_stride_1_s512_rel_contrib": 0.47480148408990913,
        "L1_desc_stride_2_s256_ratio": 1.1277518638227961,
        "L1_desc_stride_2_s256_delta_norm": 26.119146943092346,
        "L1_desc_stride_2_s256_rel_contrib": 0.4277846002471307,
        "L1_desc_stride_3_s128_ratio": 1.1035389148733292,
        "L1_desc_stride_3_s128_delta_norm": 26.893393754959106,
        "L1_desc_stride_3_s128_rel_contrib": 0.4011195185026484,
        "L1_desc_stride_4_s64_ratio": 1.0834458907312112,
        "L1_desc_stride_4_s64_delta_norm": 26.948425889015198,
        "L1_desc_stride_4_s64_rel_contrib": 0.3708599223513499,
        "L1_desc_stride_5_s32_ratio": 1.0635556495965162,
        "L1_desc_stride_5_s32_delta_norm": 25.809901118278503,
        "L1_desc_stride_5_s32_rel_contrib": 0.3295135570560245,
        "L1_desc_stride_6_s16_ratio": 1.0489816835377448,
        "L1_desc_stride_6_s16_delta_norm": 24.039377689361572,
        "L1_desc_stride_6_s16_rel_contrib": 0.28831933867429893,
        "L1_desc_stride_7_s8_ratio": 1.0313837961080419,
        "L1_desc_stride_7_s8_delta_norm": 21.671804547309875,
        "L1_desc_stride_7_s8_rel_contrib": 0.24719136087657445,
        "L1_desc_stride_8_s1_ratio": 1.0127236035061289,
        "L1_desc_stride_8_s1_delta_norm": 17.592942714691162,
        "L1_desc_stride_8_s1_rel_contrib": 0.19344017680708614,
        "L1_desc_stride_mean_ratio": 1.1060988846368034,
        "L0_desc_stride_0_s1024_ratio": 1.1704133089915765,
        "L0_desc_stride_0_s1024_delta_norm": 26.420713424682617,
        "L0_desc_stride_0_s1024_rel_contrib": 0.45757930722144796,
        "L0_desc_stride_1_s512_ratio": 1.1107398249836928,
        "L0_desc_stride_1_s512_delta_norm": 25.7926824092865,
        "L0_desc_stride_1_s512_rel_contrib": 0.4028673069545152,
        "L0_desc_stride_2_s256_ratio": 1.089615783921214,
        "L0_desc_stride_2_s256_delta_norm": 26.023430585861206,
        "L0_desc_stride_2_s256_rel_contrib": 0.37640160082168794,
        "L0_desc_stride_3_s128_ratio": 1.0803713646134583,
        "L0_desc_stride_3_s128_delta_norm": 26.892073035240173,
        "L0_desc_stride_3_s128_rel_contrib": 0.3616679308973825,
        "L0_desc_stride_4_s64_ratio": 1.0694550184368854,
        "L0_desc_stride_4_s64_delta_norm": 27.265494465827942,
        "L0_desc_stride_4_s64_rel_contrib": 0.34377655080531777,
        "L0_desc_stride_5_s32_ratio": 1.0526233512956868,
        "L0_desc_stride_5_s32_delta_norm": 25.792479634284973,
        "L0_desc_stride_5_s32_rel_contrib": 0.3051892815759411,
        "L0_desc_stride_6_s16_ratio": 1.04214465994224,
        "L0_desc_stride_6_s16_delta_norm": 24.089585423469543,
        "L0_desc_stride_6_s16_rel_contrib": 0.2704565323831673,
        "L0_desc_stride_7_s8_ratio": 1.0269256632270731,
        "L0_desc_stride_7_s8_delta_norm": 21.530233025550842,
        "L0_desc_stride_7_s8_rel_contrib": 0.23170651139506,
        "L0_desc_stride_8_s1_ratio": 1.0112945202118568,
        "L0_desc_stride_8_s1_delta_norm": 17.90680718421936,
        "L0_desc_stride_8_s1_rel_contrib": 0.1867318611994409,
        "L0_desc_stride_mean_ratio": 1.0726203884026315
      },
      "hilberg": {},
      "embed_norm": 21.68494939804077
    },
    "strata": {
      "prose": {
        "L0_asc": {
          "mean_ratio": -0.7112922396864407,
          "std_ratio": 0.14205540967399477,
          "mean_h_in": -0.1786259226500988,
          "mean_h_out": 0.12526337057352066,
          "phi_dev": 1.3293262284363356,
          "direction": "compressing"
        },
        "L1_asc": {
          "mean_ratio": 5.193356060821078,
          "std_ratio": 0.47526513581986285,
          "mean_h_in": 0.12526337057352066,
          "mean_h_out": 0.6432755291461945,
          "phi_dev": 4.575322072071183,
          "direction": "expanding"
        },
        "L2_apex": {
          "mean_ratio": 1.7497820915725562,
          "std_ratio": 0.016961196213838604,
          "mean_h_in": 0.6432755291461945,
          "mean_h_out": 1.1251767873764038,
          "phi_dev": 1.1317481028226615,
          "direction": "expanding"
        },
        "L1_desc": {
          "mean_ratio": 1.3006096031372485,
          "std_ratio": 0.011633890165253782,
          "mean_h_in": 1.1251767873764038,
          "mean_h_out": 1.4631774723529816,
          "phi_dev": 0.6825756143873537,
          "direction": "expanding"
        },
        "L0_desc": {
          "mean_ratio": 1.225549012166969,
          "std_ratio": 0.007128254375281221,
          "mean_h_in": 1.4631774723529816,
          "mean_h_out": 1.792902559041977,
          "phi_dev": 0.6075150234170742,
          "direction": "expanding"
        },
        "aggregate": {
          "mean_ratio": 1.751600905602282,
          "mean_phi_dev": 1.6652974082269214,
          "target": 0.6180339887498948
        },
        "loss": {
          "mean_loss": 7.451181888580322,
          "relational_loss": 0.630650334389583,
          "excess_ppl": 317.7236210168202
        }
      },
      "compositional": {
        "L0_asc": {
          "mean_ratio": -0.6103972565952984,
          "std_ratio": 0.029133903666402866,
          "mean_h_in": -0.18777081742882729,
          "mean_h_out": 0.11451614089310169,
          "phi_dev": 1.228431245345193,
          "direction": "compressing"
        },
        "L1_asc": {
          "mean_ratio": 5.320506399297366,
          "std_ratio": 0.20130843965521852,
          "mean_h_in": 0.11451614089310169,
          "mean_h_out": 0.6087831407785416,
          "phi_dev": 4.702472410547471,
          "direction": "expanding"
        },
        "L2_apex": {
          "mean_ratio": 1.7386434616621502,
          "std_ratio": 0.022953880492720097,
          "mean_h_in": 0.6087831407785416,
          "mean_h_out": 1.0586907267570496,
          "phi_dev": 1.1206094729122555,
          "direction": "expanding"
        },
        "L1_desc": {
          "mean_ratio": 1.3290923227839653,
          "std_ratio": 0.017150509374971066,
          "mean_h_in": 1.0586907267570496,
          "mean_h_out": 1.4065018594264984,
          "phi_dev": 0.7110583340340705,
          "direction": "expanding"
        },
        "L0_desc": {
          "mean_ratio": 1.2313054480389423,
          "std_ratio": 0.008274446943197003,
          "mean_h_in": 1.4065018594264984,
          "mean_h_out": 1.7315919399261475,
          "phi_dev": 0.6132714592890475,
          "direction": "expanding"
        },
        "aggregate": {
          "mean_ratio": 1.8018300750374252,
          "mean_phi_dev": 1.6751685844256072,
          "target": 0.6180339887498948
        },
        "loss": {
          "mean_loss": 7.492370009422302,
          "relational_loss": 0.6351590103321636,
          "excess_ppl": 331.08330134926257
        }
      },
      "technical": {
        "L0_asc": {
          "mean_ratio": -0.75521519946894,
          "std_ratio": 0.12193725995868906,
          "mean_h_in": -0.1693057119846344,
          "mean_h_out": 0.12752235122025013,
          "phi_dev": 1.3732491882188347,
          "direction": "compressing"
        },
        "L1_asc": {
          "mean_ratio": 5.236980120481141,
          "std_ratio": 0.5957659250924615,
          "mean_h_in": 0.12752235122025013,
          "mean_h_out": 0.6574892848730087,
          "phi_dev": 4.618946131731246,
          "direction": "expanding"
        },
        "L2_apex": {
          "mean_ratio": 1.7514986353345374,
          "std_ratio": 0.029614369665342196,
          "mean_h_in": 0.6574892848730087,
          "mean_h_out": 1.1506148874759674,
          "phi_dev": 1.1334646465846427,
          "direction": "expanding"
        },
        "L1_desc": {
          "mean_ratio": 1.2954432335563955,
          "std_ratio": 0.0086509329295611,
          "mean_h_in": 1.1506148874759674,
          "mean_h_out": 1.490507960319519,
          "phi_dev": 0.6774092448065007,
          "direction": "expanding"
        },
        "L0_desc": {
          "mean_ratio": 1.222922163099643,
          "std_ratio": 0.008924588749514052,
          "mean_h_in": 1.490507960319519,
          "mean_h_out": 1.822412371635437,
          "phi_dev": 0.6048881743497482,
          "direction": "expanding"
        },
        "aggregate": {
          "mean_ratio": 1.7503257906005552,
          "mean_phi_dev": 1.6815914771381943,
          "target": 0.6180339887498948
        },
        "loss": {
          "mean_loss": 8.27717673778534,
          "relational_loss": 0.7210682274416598,
          "excess_ppl": 725.7290514419386
        }
      },
      "math": {
        "L0_asc": {
          "mean_ratio": 0.13418526415412568,
          "std_ratio": 0.17214387179911841,
          "mean_h_in": -0.20276298373937607,
          "mean_h_out": -0.026290489360690117,
          "phi_dev": 0.4838487245957691,
          "direction": "compressing"
        },
        "L1_asc": {
          "mean_ratio": -2.457242991670432,
          "std_ratio": 15.537354389759907,
          "mean_h_in": -0.026290489360690117,
          "mean_h_out": 0.3455006256699562,
          "phi_dev": 3.075276980420327,
          "direction": "compressing"
        },
        "L2_apex": {
          "mean_ratio": 2.0426035306837758,
          "std_ratio": 0.19024296897232248,
          "mean_h_in": 0.3455006256699562,
          "mean_h_out": 0.6926845759153366,
          "phi_dev": 1.4245695419338809,
          "direction": "expanding"
        },
        "L1_desc": {
          "mean_ratio": 1.4156581264220531,
          "std_ratio": 0.033261603374496546,
          "mean_h_in": 0.6926845759153366,
          "mean_h_out": 0.9777094721794128,
          "phi_dev": 0.7976241376721583,
          "direction": "expanding"
        },
        "L0_desc": {
          "mean_ratio": 1.2785224528023247,
          "std_ratio": 0.017522576435433975,
          "mean_h_in": 0.9777094721794128,
          "mean_h_out": 1.247761458158493,
          "phi_dev": 0.6604884640524299,
          "direction": "expanding"
        },
        "aggregate": {
          "mean_ratio": 0.4827452764783695,
          "mean_phi_dev": 1.2883615697349131,
          "target": 0.6180339887498948
        },
        "loss": {
          "mean_loss": 7.437026739120483,
          "relational_loss": 0.6291008346666396,
          "excess_ppl": 313.2578768781369
        }
      }
    }
  },
  "n_probes": 40,
  "n_lambda": 1,
  "compile_results": [
    {
      "probe_id": "cg-strong-01",
      "category": "strong_compile",
      "gradient": 1.0,
      "prompt": "The dog runs.",
      "gate_used": "compile",
      "generation": "\n    const_comment>username_start><issue_comment>username_comment>username_",
      "has_lambda": false,
      "elapsed_ms": 114.6
    },
    {
      "probe_id": "cg-strong-02",
      "category": "strong_compile",
      "gradient": 1.0,
      "prompt": "Every student reads a book.",
      "gate_used": "compile",
      "generation": "\n<issue_comment>username__comment>username__comment>username_comment>",
      "has_lambda": false,
      "elapsed_ms": 160.3
    },
    {
      "probe_id": "cg-strong-03",
      "category": "strong_compile",
      "gradient": 1.0,
      "prompt": "The cat that sat on the mat is black.",
      "gate_used": "compile",
      "generation": "\n<issue_______comment>username_comment>usernameusername_comment",
      "has_lambda": false,
      "elapsed_ms": 41.2
    },
    {
      "probe_id": "cg-strong-04",
      "category": "strong_compile",
      "gradient": 1.0,
      "prompt": "If it rains, the ground is wet.",
      "gate_used": "compile",
      "generation": "\n            constconstconst {\n<issue__comment>username____",
      "has_lambda": false,
      "elapsed_ms": 203.3
    },
    {
      "probe_id": "cg-strong-05",
      "category": "strong_compile",
      "gradient": 1.0,
      "prompt": "No bird can swim.",
      "gate_used": "compile",
      "generation": "\n    _comment>username__comment>username____comment>username_comment",
      "has_lambda": false,
      "elapsed_ms": 126.9
    },
    {
      "probe_id": "cg-strong-06",
      "category": "strong_compile",
      "gradient": 1.0,
      "prompt": "The teacher gave every student a grade.",
      "gate_used": "compile",
      "generation": "\n    const {\n            constconstconst {\n<issue_comment>username_",
      "has_lambda": false,
      "elapsed_ms": 58.5
    },
    {
      "probe_id": "cg-strong-07",
      "category": "strong_compile",
      "gradient": 1.0,
      "prompt": "Someone believes that the earth is flat.",
      "gate_used": "compile",
      "generation": "\n<issue__comment>username__comment>username_comment>username___",
      "has_lambda": false,
      "elapsed_ms": 111.1
    },
    {
      "probe_id": "cg-strong-08",
      "category": "strong_compile",
      "gradient": 1.0,
      "prompt": "Birds fly.",
      "gate_used": "compile",
      "generation": "\n<issue_comment>username_comment>username_comment>username_comment>username_",
      "has_lambda": false,
      "elapsed_ms": 118.6
    },
    {
      "probe_id": "cg-medium-01",
      "category": "medium_compile",
      "gradient": 0.7,
      "prompt": "The old man walked slowly across the bridge.",
      "gate_used": "compile",
      "generation": "\n            const {\n            }\n<issue_comment>username_comment",
      "has_lambda": false,
      "elapsed_ms": 95.2
    },
    {
      "probe_id": "cg-medium-02",
      "category": "medium_compile",
      "gradient": 0.7,
      "prompt": "Three children were playing in the garden while their mother watched.",
      "gate_used": "compile",
      "generation": "\n        const {\n<issue_comment>username___comment>username__",
      "has_lambda": false,
      "elapsed_ms": 85.3
    },
    {
      "probe_id": "cg-medium-03",
      "category": "medium_compile",
      "gradient": 0.7,
      "prompt": "The book that I bought yesterday was expensive.",
      "gate_used": "compile",
      "generation": "\n            return:\n    return \"<issue_comment>username_comment>username",
      "has_lambda": false,
      "elapsed_ms": 129.3
    },
    {
      "probe_id": "cg-medium-04",
      "category": "medium_compile",
      "gradient": 0.6,
      "prompt": "Most politicians promise more than they deliver.",
      "gate_used": "compile",
      "generation": "\n    const {\n                    this.\n                    constconst",
      "has_lambda": false,
      "elapsed_ms": 106.5
    },
    {
      "probe_id": "cg-medium-05",
      "category": "medium_compile",
      "gradient": 0.6,
      "prompt": "The fact that she left surprised nobody.",
      "gate_used": "compile",
      "generation": "\n                                }\n    return {\n\n                ",
      "has_lambda": false,
      "elapsed_ms": 142.5
    },
    {
      "probe_id": "cg-medium-06",
      "category": "medium_compile",
      "gradient": 0.5,
      "prompt": "Running is healthier than sitting.",
      "gate_used": "compile",
      "generation": "\n<issue__comment>username_comment>username__comment>username_comment>",
      "has_lambda": false,
      "elapsed_ms": 79.1
    },
    {
      "probe_id": "cg-medium-07",
      "category": "medium_compile",
      "gradient": 0.6,
      "prompt": "She told him to leave before it got dark.",
      "gate_used": "compile",
      "generation": "\n<issue_________________",
      "has_lambda": false,
      "elapsed_ms": 79.1
    },
    {
      "probe_id": "cg-medium-08",
      "category": "medium_compile",
      "gradient": 0.6,
      "prompt": "What the witness saw contradicted the official report.",
      "gate_used": "compile",
      "generation": "\n<issue_____comment>username_comment>username_____",
      "has_lambda": false,
      "elapsed_ms": 111.7
    },
    {
      "probe_id": "cg-weak-01",
      "category": "weak_compile",
      "gradient": 0.3,
      "prompt": "\u03bbx.\u03bby. (f x) \u2227 (g y)",
      "gate_used": "compile",
      "generation": "\n\\\\\\\\\\\\\\\\\\\\\\\\\\\\\\\\\\\\\\",
      "has_lambda": true,
      "elapsed_ms": 109.9
    },
    {
      "probe_id": "cg-weak-02",
      "category": "weak_compile",
      "gradient": 0.3,
      "prompt": "In formal semantics, Montague grammar provides a framework for natural language meaning.",
      "gate_used": "compile",
      "generation": "\n    constconst {\n<issue_comment>username__comment>username___",
      "has_lambda": false,
      "elapsed_ms": 134.3
    },
    {
      "probe_id": "cg-weak-03",
      "category": "weak_compile",
      "gradient": 0.3,
      "prompt": "\u2200x. P(x) \u2192 Q(x) is a valid first-order logic formula.",
      "gate_used": "compile",
      "generation": "\n        const {\n                const_______comment>",
      "has_lambda": false,
      "elapsed_ms": 77.8
    },
    {
      "probe_id": "cg-weak-04",
      "category": "weak_compile",
      "gradient": 0.2,
      "prompt": "Define a function that maps strings to their lengths.",
      "gate_used": "compile",
      "generation": "\n        constconstconst {\n<issue__________",
      "has_lambda": false,
      "elapsed_ms": 71.8
    },
    {
      "probe_id": "cg-weak-05",
      "category": "weak_compile",
      "gradient": 0.2,
      "prompt": "The type signature is Int -> String -> Bool.",
      "gate_used": "compile",
      "generation": "\n        }\n<issue___comment>username_comment>username___",
      "has_lambda": false,
      "elapsed_ms": 113.9
    },
    {
      "probe_id": "cg-weak-06",
      "category": "weak_compile",
      "gradient": 0.15,
      "prompt": "Translate the following from English to French: The cat is sleeping.",
      "gate_used": "compile",
      "generation": "\n<issue__comment>username_comment>username_comment>username__comment>",
      "has_lambda": false,
      "elapsed_ms": 106.5
    },
    {
      "probe_id": "cg-weak-07",
      "category": "weak_compile",
      "gradient": 0.25,
      "prompt": "Parse the sentence: The dog bit the man.",
      "gate_used": "compile",
      "generation": "\n<issue__comment>username__comment>username_comment>username__comment",
      "has_lambda": false,
      "elapsed_ms": 119.2
    },
    {
      "probe_id": "cg-weak-08",
      "category": "weak_compile",
      "gradient": 0.4,
      "prompt": "What is the logical form of 'All men are mortal'?",
      "gate_used": "compile",
      "generation": "\n<issue_comment>username_comment>username_comment>username_comment>username_",
      "has_lambda": false,
      "elapsed_ms": 75.7
    },
    {
      "probe_id": "cg-null-01",
      "category": "null",
      "gradient": 0.0,
      "prompt": "What is the capital of France?",
      "gate_used": "null",
      "generation": "\nThe first first first first time to the end of the same time to the the most of the",
      "has_lambda": false,
      "elapsed_ms": 221.4
    },
    {
      "probe_id": "cg-null-02",
      "category": "null",
      "gradient": 0.0,
      "prompt": "How are you today?",
      "gate_used": "null",
      "generation": "\n\n\n\n\n\n\n\n\n\n\n\n\n\n\n\n\n\n\n\n",
      "has_lambda": false,
      "elapsed_ms": 251.0
    },
    {
      "probe_id": "cg-null-03",
      "category": "null",
      "gradient": 0.0,
      "prompt": "Explain what photosynthesis is.",
      "gate_used": "null",
      "generation": "\nI'm not not not not be seen.\nI am am am a lot of the same",
      "has_lambda": false,
      "elapsed_ms": 107.1
    },
    {
      "probe_id": "cg-null-04",
      "category": "null",
      "gradient": 0.0,
      "prompt": "List three primary colors.",
      "gate_used": "null",
      "generation": "\nTheThe most most of the the the same same time of the same time to be a a",
      "has_lambda": false,
      "elapsed_ms": 98.5
    },
    {
      "probe_id": "cg-null-05",
      "category": "null",
      "gradient": 0.0,
      "prompt": "Write a haiku about rain.",
      "gate_used": "null",
      "generation": "\nTheTheThe fact is a great great great way to be a lot of the the most of",
      "has_lambda": false,
      "elapsed_ms": 97.8
    },
    {
      "probe_id": "cg-null-06",
      "category": "null",
      "gradient": 0.0,
      "prompt": "What year was the first moon landing?",
      "gate_used": "null",
      "generation": "\nI\u2019tttt.\nI am am am am a lot of the same time",
      "has_lambda": false,
      "elapsed_ms": 30.9
    },
    {
      "probe_id": "cg-null-07",
      "category": "null",
      "gradient": 0.0,
      "prompt": "Summarize the water cycle in one sentence.",
      "gate_used": "null",
      "generation": "\n--based----------------",
      "has_lambda": false,
      "elapsed_ms": 76.5
    },
    {
      "probe_id": "cg-null-08",
      "category": "null",
      "gradient": 0.0,
      "prompt": "What is 7 times 8?",
      "gate_used": "null",
      "generation": "\n\nII'm'm not not be seen.\nI am am am am a lot of",
      "has_lambda": false,
      "elapsed_ms": 104.6
    },
    {
      "probe_id": "cg-anti-01",
      "category": "anti_compile",
      "gradient": 0.0,
      "prompt": "Tell me a joke.",
      "gate_used": "null",
      "generation": "\n\n\n\n\n\n\n\n\n\n\n\n\n\n\n\n\n\n\n\n",
      "has_lambda": false,
      "elapsed_ms": 89.3
    },
    {
      "probe_id": "cg-anti-02",
      "category": "anti_compile",
      "gradient": 0.0,
      "prompt": "What should I have for dinner tonight?",
      "gate_used": "null",
      "generation": " I I I I I I I I I I I I I I I I I I I I",
      "has_lambda": false,
      "elapsed_ms": 109.6
    },
    {
      "probe_id": "cg-anti-03",
      "category": "anti_compile",
      "gradient": 0.0,
      "prompt": "How do I fix a leaky faucet?",
      "gate_used": "null",
      "generation": "\nI'm not be able to be.\nI don\u2019ttttttt",
      "has_lambda": false,
      "elapsed_ms": 51.6
    },
    {
      "probe_id": "cg-anti-04",
      "category": "anti_compile",
      "gradient": 0.0,
      "prompt": "Is it going to rain tomorrow?",
      "gate_used": "null",
      "generation": "\nII'm going to be able to be a lot of the way to be a lot of",
      "has_lambda": false,
      "elapsed_ms": 75.2
    },
    {
      "probe_id": "cg-anti-05",
      "category": "anti_compile",
      "gradient": 0.0,
      "prompt": "Who won the last World Cup?",
      "gate_used": "null",
      "generation": "\n\n\n\n\n\n\n\n\n\n\n\n\n\n\n\n\n\n\n\n",
      "has_lambda": false,
      "elapsed_ms": 139.2
    },
    {
      "probe_id": "cg-anti-06",
      "category": "anti_compile",
      "gradient": 0.0,
      "prompt": "Recommend a good book to read.",
      "gate_used": "null",
      "generation": "\nII think I'm not not not not not.\nIII'm'm'm'm",
      "has_lambda": false,
      "elapsed_ms": 107.5
    },
    {
      "probe_id": "cg-anti-07",
      "category": "anti_compile",
      "gradient": 0.0,
      "prompt": "What is your favorite color?",
      "gate_used": "null",
      "generation": "\n\nIIII'm'm'm not not not not.\nIIIII",
      "has_lambda": false,
      "elapsed_ms": 142.5
    },
    {
      "probe_id": "cg-anti-08",
      "category": "anti_compile",
      "gradient": 0.0,
      "prompt": "Convert 72 degrees Fahrenheit to Celsius.",
      "gate_used": "null",
      "generation": "\n\n\u2022\u2022\u2022\n\n\n\n\n\n\n\n\n\n\n\n\n\n\n",
      "has_lambda": false,
      "elapsed_ms": 31.9
    }
  ]
}